nanonisTCP/AutoApproach.py
nanonisTCP/Bias.py
nanonisTCP/BiasSpectr.py
nanonisTCP/Current.py
nanonisTCP/FolMe.py
nanonisTCP/LockIn.py
nanonisTCP/Marks.py
nanonisTCP/Motor.py
nanonisTCP/Osci2T.py
nanonisTCP/Pattern.py
nanonisTCP/Piezo.py
nanonisTCP/SafeTip.py
nanonisTCP/Scan.py
nanonisTCP/Signals.py
nanonisTCP/TipRec.py
nanonisTCP/TipShaper.py
nanonisTCP/UserOut.py
nanonisTCP/Util.py
nanonisTCP/ZController.py
nanonisTCP/__init__.py
nanonisTCP/nanonisTCP.py
nanonisTCP/test/AutoApproachTest.py
nanonisTCP/test/BiasSpectrTest.py
nanonisTCP/test/BiasTest.py
nanonisTCP/test/CurrentTest.py
nanonisTCP/test/FolMeTest.py
nanonisTCP/test/LockInTest.py
nanonisTCP/test/MarksTest.py
nanonisTCP/test/MotorTest.py
nanonisTCP/test/Osci2TTest.py
nanonisTCP/test/PiezoTest.py
nanonisTCP/test/SafeTipTest.py
nanonisTCP/test/ScanTest.py
nanonisTCP/test/SignalsTest.py
nanonisTCP/test/TipRecTest.py
nanonisTCP/test/TipShaperTest.py
nanonisTCP/test/UserOutTest.py
nanonisTCP/test/UtilTest.py
nanonisTCP/test/ZControllerTest.py
nanonisTCP/test/__init__.py
nanonisTCP/test/test.py
nanonistcp-1.1.5.dist-info/licenses/LICENSE
nanonistcp-1.1.5.dist-info/METADATA
nanonistcp-1.1.5.dist-info/WHEEL
nanonistcp-1.1.5.dist-info/top_level.txt
nanonistcp-1.1.5.dist-info/RECORD
