Metadata-Version: 2.4
Name: nanonisTCP
Version: 1.1.5
Summary: python module for communicating via nanonis TCP protocal
Home-page: https://github.com/New-Horizons-SPM/nanonisTCP
Author: Julian Ceddia
Author-email: jdceddia@gmail.com
License: MIT
Project-URL: Bug Tracker, https://github.com/New-Horizons-SPM/nanonisTCP/issues
License-File: LICENSE
Requires-Dist: numpy
Requires-Dist: matplotlib
Dynamic: author
Dynamic: author-email
Dynamic: description
Dynamic: description-content-type
Dynamic: home-page
Dynamic: license
Dynamic: license-file
Dynamic: project-url
Dynamic: requires-dist
Dynamic: summary
